<?xml version="1.0"?>
<!DOCTYPE hibernate-mapping PUBLIC "-//Hibernate/Hibernate Mapping DTD 3.0//EN"
"http://hibernate.sourceforge.net/hibernate-mapping-3.0.dtd">
<!-- Generated 28-ene-2010 12:33:16 by Hibernate Tools 3.2.4.GA -->
<hibernate-mapping>
    <class name="es.dipucadiz.etir.comun.dto.DocumentoContadorDTO" table="GA_DOCUMENTO_CONTADOR">
        <composite-id name="id" class="es.dipucadiz.etir.comun.dto.DocumentoContadorDTOId">
            <key-property name="coModelo" type="string">
                <column name="CO_MODELO" length="3" />
            </key-property>
            <key-property name="coVersion" type="string">
                <column name="CO_VERSION" length="1" />
            </key-property>
        </composite-id>
        <!-- <one-to-one name="modeloVersionDTO" class="es.dipucadiz.etir.comun.dto.ModeloVersionDTO" constrained="true"></one-to-one> -->
        <many-to-one name="modeloVersionDTO" class="es.dipucadiz.etir.comun.dto.ModeloVersionDTO" unique="true" insert="false" update="false">
	        <column name="CO_MODELO" length="3" not-null="true" />
	        <column name="CO_VERSION" length="1" not-null="true" />
        </many-to-one>
        <property name="nuDocumento" type="int">
            <column name="NU_DOCUMENTO" precision="8" scale="0" not-null="true" />
        </property>
        <property name="fhActualizacion" type="timestamp">
            <column name="FH_ACTUALIZACION" length="11" />
        </property>
        <property name="coUsuarioActualizacion" type="string">
            <column name="CO_USUARIO_ACTUALIZACION" length="10" />
        </property>
        <property name="rowid" type="string" update="false" insert="false">
        	  <column name="ROWID" length="18" />
        </property>
    </class>
</hibernate-mapping>
